RippleDownCounter_4bit.v
module RippleDownCounter_4bit(clk, rst, count);
	input clk, rst;
	output [3:0] count;
	
	DFlipFlop d0 (.q(count[0]), .qBar(), .D(~count[0]), .clk(clk), .rst(rst));
	DFlipFlop d1 (.q(count[1]), .qBar(), .D(~count[1]), .clk(count[0]), .rst(rst));
	DFlipFlop d2 (.q(count[2]), .qBar(), .D(~count[2]), .clk(count[1]), .rst(rst));
	DFlipFlop d3 (.q(count[3]), .qBar(), .D(~count[3]), .clk(count[2]), .rst(rst));
endmodule 

module DFlipFlop(q, qBar, D, clk, rst);
	input D, clk, rst;
	output q, qBar;
	reg q;
	not n1 (qBar, q);
	always@ (negedge rst or posedge clk)
	begin
	if(!rst)
	q = 0;
	else
	q = D;
	end
endmodule


module RippleDownCounter_4bit_testbench;
	reg clk, rst;
	wire [3:0] count;

	RippleDownCounter_4bit counter (clk, rst, count);
	
	parameter clk_PERIOD=10;
	initial clk=1;
	always begin
		#(clk_PERIOD/2);
		clk = ~clk;
	end 
	
	initial begin 
	$dumpfile("RippleDownCounter_4bit.vcd");
	$dumpvars(0, RippleDownCounter_4bit_testbench);
	
					@(posedge clk);
	rst <= 0;		@(posedge clk);
					@(posedge clk);
					@(posedge clk);
	rst = 1;		@(posedge clk);
					@(posedge clk);
					@(posedge clk);
					@(posedge clk);
					@(posedge clk);
					@(posedge clk);
					@(posedge clk);
					@(posedge clk);
					@(posedge clk);
					@(posedge clk);
					@(posedge clk);
					@(posedge clk);
					@(posedge clk);
					@(posedge clk);
					@(posedge clk);
					@(posedge clk);
					@(posedge clk);
					@(posedge clk);
	rst <= 0;		@(posedge clk);
					@(posedge clk);
					@(posedge clk);
	rst = 1;		@(posedge clk);
					@(posedge clk);
					@(posedge clk);
					@(posedge clk);
					@(posedge clk);
					@(posedge clk);
					@(posedge clk);
					@(posedge clk);
					@(posedge clk);
					@(posedge clk);
					@(posedge clk);
					@(posedge clk);
					@(posedge clk);
					@(posedge clk);
					@(posedge clk);
					@(posedge clk);
					@(posedge clk);
					@(posedge clk);
					@(posedge clk);
					@(posedge clk);
					@(posedge clk);
					@(posedge clk);
					@(posedge clk);
					@(posedge clk);
					@(posedge clk);
					@(posedge clk) $finish;
	end 
	
endmodule

RippleDownCounter_4bit.vcd
$date
	Sun Apr 03 19:36:09 2016
$end
$version
	Icarus Verilog
$end
$timescale
	1s
$end
$scope module RippleDownCounter_4bit_testbench $end
$var wire 4 ! count [3:0] $end
$var reg 1 " clk $end
$var reg 1 # rst $end
$scope module counter $end
$var wire 1 $ clk $end
$var wire 4 % count [3:0] $end
$var wire 1 & rst $end
$scope module d0 $end
$var wire 1 ' D $end
$var wire 1 $ clk $end
$var wire 1 ( qBar $end
$var wire 1 & rst $end
$var reg 1 ) q $end
$upscope $end
$scope module d1 $end
$var wire 1 * D $end
$var wire 1 + clk $end
$var wire 1 , qBar $end
$var wire 1 & rst $end
$var reg 1 - q $end
$upscope $end
$scope module d2 $end
$var wire 1 . D $end
$var wire 1 / clk $end
$var wire 1 0 qBar $end
$var wire 1 & rst $end
$var reg 1 1 q $end
$upscope $end
$scope module d3 $end
$var wire 1 2 D $end
$var wire 1 3 clk $end
$var wire 1 4 qBar $end
$var wire 1 & rst $end
$var reg 1 5 q $end
$upscope $end
$upscope $end
$upscope $end
$enddefinitions $end
#0
$dumpvars
x5
x4
x3
x2
x1
x0
x/
x.
x-
x,
z+
x*
z)
x(
x'
x&
bxz %
1$
x#
1"
bxz !
$end
#5
0"
0$
#10
12
1.
1*
1'
14
10
03
1,
0/
1(
05
01
0-
0#
0&
0+
0)
b0 !
b0 %
1"
1$
#15
0"
0$
#20
1"
1$
#25
0"
0$
#30
1"
1$
#35
0"
0$
#40
02
04
0.
15
00
13
0*
11
0,
1/
0'
1-
0(
1+
1)
b1111 !
b1111 %
1#
1&
1"
1$
#45
0"
0$
#50
1'
1(
0+
0)
b1110 !
b1110 %
1"
1$
#55
0"
0$
#60
1*
1,
0/
0'
0-
0(
1+
1)
b1101 !
b1101 %
1"
1$
#65
0"
0$
#70
1'
1(
0+
0)
b1100 !
b1100 %
1"
1$
#75
0"
0$
#80
1.
10
03
0*
01
0,
1/
0'
1-
0(
1+
1)
b1011 !
b1011 %
1"
1$
#85
0"
0$
#90
1'
1(
0+
0)
b1010 !
b1010 %
1"
1$
#95
0"
0$
#100
1*
1,
0/
0'
0-
0(
1+
1)
b1001 !
b1001 %
1"
1$
#105
0"
0$
#110
1'
1(
0+
0)
b1000 !
b1000 %
1"
1$
#115
0"
0$
#120
12
14
0.
05
00
13
0*
11
0,
1/
0'
1-
0(
1+
1)
b111 !
b111 %
1"
1$
#125
0"
0$
#130
1'
1(
0+
0)
b110 !
b110 %
1"
1$
#135
0"
0$
#140
1*
1,
0/
0'
0-
0(
1+
1)
b101 !
b101 %
1"
1$
#145
0"
0$
#150
1'
1(
0+
0)
b100 !
b100 %
1"
1$
#155
0"
0$
#160
1.
10
03
0*
01
0,
1/
0'
1-
0(
1+
1)
b11 !
b11 %
1"
1$
#165
0"
0$
#170
1'
1(
0+
0)
b10 !
b10 %
1"
1$
#175
0"
0$
#180
1*
1,
0/
0'
0-
0(
1+
1)
b1 !
b1 %
1"
1$
#185
0"
0$
#190
1'
1(
0+
0)
b0 !
b0 %
1"
1$
#195
0"
0$
#200
02
04
0.
15
00
13
0*
11
0,
1/
0'
1-
0(
1+
1)
b1111 !
b1111 %
1"
1$
#205
0"
0$
#210
1'
1(
0+
0)
b1110 !
b1110 %
1"
1$
#215
0"
0$
#220
12
1.
14
10
03
05
01
0#
0&
1*
1,
0/
1'
0-
1(
0+
0)
b0 !
b0 %
1"
1$
#225
0"
0$
#230
1"
1$
#235
0"
0$
#240
1"
1$
#245
0"
0$
#250
02
04
0.
15
00
13
0*
11
0,
1/
0'
1-
0(
1+
1)
b1111 !
b1111 %
1#
1&
1"
1$
#255
0"
0$
#260
1'
1(
0+
0)
b1110 !
b1110 %
1"
1$
#265
0"
0$
#270
1*
1,
0/
0'
0-
0(
1+
1)
b1101 !
b1101 %
1"
1$
#275
0"
0$
#280
1'
1(
0+
0)
b1100 !
b1100 %
1"
1$
#285
0"
0$
#290
1.
10
03
0*
01
0,
1/
0'
1-
0(
1+
1)
b1011 !
b1011 %
1"
1$
#295
0"
0$
#300
1'
1(
0+
0)
b1010 !
b1010 %
1"
1$
#305
0"
0$
#310
1*
1,
0/
0'
0-
0(
1+
1)
b1001 !
b1001 %
1"
1$
#315
0"
0$
#320
1'
1(
0+
0)
b1000 !
b1000 %
1"
1$
#325
0"
0$
#330
12
14
0.
05
00
13
0*
11
0,
1/
0'
1-
0(
1+
1)
b111 !
b111 %
1"
1$
#335
0"
0$
#340
1'
1(
0+
0)
b110 !
b110 %
1"
1$
#345
0"
0$
#350
1*
1,
0/
0'
0-
0(
1+
1)
b101 !
b101 %
1"
1$
#355
0"
0$
#360
1'
1(
0+
0)
b100 !
b100 %
1"
1$
#365
0"
0$
#370
1.
10
03
0*
01
0,
1/
0'
1-
0(
1+
1)
b11 !
b11 %
1"
1$
#375
0"
0$
#380
1'
1(
0+
0)
b10 !
b10 %
1"
1$
#385
0"
0$
#390
1*
1,
0/
0'
0-
0(
1+
1)
b1 !
b1 %
1"
1$
#395
0"
0$
#400
1'
1(
0+
0)
b0 !
b0 %
1"
1$
#405
0"
0$
#410
02
04
0.
15
00
13
0*
11
0,
1/
0'
1-
0(
1+
1)
b1111 !
b1111 %
1"
1$
#415
0"
0$
#420
1'
1(
0+
0)
b1110 !
b1110 %
1"
1$
#425
0"
0$
#430
1*
1,
0/
0'
0-
0(
1+
1)
b1101 !
b1101 %
1"
1$
#435
0"
0$
#440
1'
1(
0+
0)
b1100 !
b1100 %
1"
1$
#445
0"
0$
#450
1.
10
03
0*
01
0,
1/
0'
1-
0(
1+
1)
b1011 !
b1011 %
1"
1$
#455
0"
0$
#460
1'
1(
0+
0)
b1010 !
b1010 %
1"
1$
#465
0"
0$
#470
1*
1,
0/
0'
0-
0(
1+
1)
b1001 !
b1001 %
1"
1$
#475
0"
0$
#480
1'
1(
0+
0)
b1000 !
b1000 %
1"
1$
#485
0"
0$
#490
12
14
0.
05
00
13
0*
11
0,
1/
0'
1-
0(
1+
1)
b111 !
b111 %
1"
1$
#495
0"
0$
#500
1'
1(
0+
0)
b110 !
b110 %
1"
1$
#505
0"
0$
#510
1*
1,
0/
0'
0-
0(
1+
1)
b101 !
b101 %
1"
1$
